keycloakauthenticator/__init__.py
keycloakauthenticator/_version.py
keycloakauthenticator/auth.py
keycloakauthenticator/metrics.py
keycloakauthenticator/tests/__init__.py
keycloakauthenticator/tests/test_auth.py
keycloakauthenticator-4.0.2.dist-info/METADATA
keycloakauthenticator-4.0.2.dist-info/WHEEL
keycloakauthenticator-4.0.2.dist-info/top_level.txt
keycloakauthenticator-4.0.2.dist-info/RECORD
