Metadata-Version: 2.4
Name: keycloakauthenticator
Version: 4.0.2
Summary: KeyCloakAuthenticator: Authenticate JupyterHub users with KeyCloak and OIDC
Home-page: https://github.com/swan-cern/jupyterhub-extensions
Author: SWAN Admins
License: AGPL-3.0
Keywords: JupyterHub,Authenticator,SWAN,CERN
Platform: Linux
Platform: Mac OS X
Classifier: License :: OSI Approved :: GNU Affero General Public License v3
Classifier: Intended Audience :: Developers
Classifier: Intended Audience :: System Administrators
Classifier: Intended Audience :: Science/Research
Classifier: Programming Language :: Python
Classifier: Programming Language :: Python :: 3
Requires-Dist: jupyterhub
Requires-Dist: oauthenticator==16.1.0
Requires-Dist: PyJWT[crypto]>=2.0.0
Dynamic: author
Dynamic: classifier
Dynamic: description
Dynamic: description-content-type
Dynamic: home-page
Dynamic: keywords
Dynamic: license
Dynamic: platform
Dynamic: requires-dist
Dynamic: summary
